data_as_code/__init__.py
data_as_code/field.py
data_as_code/main.py
data_as_code/source.py
data_as_code/worker.py
data_as_code/data/__init__.py
tests/__init__.py
tests/test_lineage.py
data_as_code-0.0.0.dist-info/LICENSE
data_as_code-0.0.0.dist-info/METADATA
data_as_code-0.0.0.dist-info/WHEEL
data_as_code-0.0.0.dist-info/top_level.txt
data_as_code-0.0.0.dist-info/RECORD
