Metadata-Version: 2.1
Name: data-as-code
Version: 0.0.0
Summary: A framework for creating recipes to handle Data as Code (DaC)
Home-page: https://github.com/Mikuana/dac
Author: Christopher Boyd
License: UNKNOWN
Platform: UNKNOWN
Classifier: Programming Language :: Python :: 3
Classifier: License :: OSI Approved :: MIT License
Classifier: Operating System :: OS Independent
Requires-Python: >=3.8
Requires-Dist: pandas (>=1.1)
Requires-Dist: pyarrow
Requires-Dist: requests
Requires-Dist: tqdm
Provides-Extra: testing
Requires-Dist: pytest ; extra == 'testing'
Requires-Dist: pytest-mock ; extra == 'testing'
Requires-Dist: pytest-cov ; extra == 'testing'
